hop/__init__.py
hop/__main__.py
hop/_version.py
hop/abcs/__init__.py
hop/api/__init__.py
hop/api/environment.py
hop/api/manager.py
hop/bin/__init__.py
hop/bin/hop.py
hop/cli/__init__.py
hop/cli/options.py
hop/util/__init__.py
aws_ec2_tool-2024.3.13.1.54.dist-info/METADATA
aws_ec2_tool-2024.3.13.1.54.dist-info/WHEEL
aws_ec2_tool-2024.3.13.1.54.dist-info/entry_points.txt
aws_ec2_tool-2024.3.13.1.54.dist-info/top_level.txt
aws_ec2_tool-2024.3.13.1.54.dist-info/RECORD
